ndx_dynamic_routing_metadata/__init__.py
ndx_dynamic_routing_metadata/ndx-dynamic-routing-metadata.extensions.yaml
ndx_dynamic_routing_metadata/ndx-dynamic-routing-metadata.namespace.yaml
ndx_dynamic_routing_metadata/py.typed
ndx_dynamic_routing_metadata/pynwb/__init__.py
ndx_dynamic_routing_metadata/spec/create_extension_spec.py
ndx_dynamic_routing_metadata-0.1.5.dist-info/LICENSE
ndx_dynamic_routing_metadata-0.1.5.dist-info/LICENSE.txt
ndx_dynamic_routing_metadata-0.1.5.dist-info/METADATA
ndx_dynamic_routing_metadata-0.1.5.dist-info/WHEEL
ndx_dynamic_routing_metadata-0.1.5.dist-info/entry_points.txt
ndx_dynamic_routing_metadata-0.1.5.dist-info/top_level.txt
ndx_dynamic_routing_metadata-0.1.5.dist-info/RECORD
