Metadata-Version: 2.1
Name: ndx-dynamic-routing-metadata
Version: 0.1.5
Summary: Type to store metadata for dynamic routing experiments at Allen Institute
Author-email: Ben Hardcastle <ben.hardcastle@alleninstitue.org>, Arjun Sridhar <arjun.sridhar@alleninstitute.org>
License: MIT
Project-URL: Repository, https://github.com/AllenInstitute/ndx-dynamic-routing-metadata
Project-URL: Issues, https://github.com/AllenInstitute/ndx-dynamic-routing-metadata/issues
Keywords: NeurodataWithoutBorders,NWB,nwb-extension,ndx-extension
Classifier: Development Status :: 3 - Alpha
Classifier: Programming Language :: Python :: 3
Classifier: Programming Language :: Python :: 3.9
Classifier: Programming Language :: Python :: 3.10
Classifier: Programming Language :: Python :: 3.11
Classifier: License :: OSI Approved :: MIT License
Classifier: Operating System :: Microsoft :: Windows
Classifier: Operating System :: POSIX :: Linux
Requires-Python: >=3.8
License-File: LICENSE
License-File: LICENSE.txt
Requires-Dist: pynwb >=2.6.0
Requires-Dist: hdmf >=3.13.0
